fastapi_pluggable_auth/.pytest_cache/.gitignore
fastapi_pluggable_auth/.pytest_cache/CACHEDIR.TAG
fastapi_pluggable_auth/.pytest_cache/README.md
fastapi_pluggable_auth/.pytest_cache/v/cache/lastfailed
fastapi_pluggable_auth/.pytest_cache/v/cache/nodeids
fastapi_pluggable_auth/.pytest_cache/v/cache/stepwise
fastapi_pluggable_auth/__init__.py
fastapi_pluggable_auth/config.py
fastapi_pluggable_auth/dependencies.py
fastapi_pluggable_auth/email/__init__.py
fastapi_pluggable_auth/email/provider.py
fastapi_pluggable_auth/email/sender.py
fastapi_pluggable_auth/email/templates/reset.txt.jinja
fastapi_pluggable_auth/email/templates/verify.txt.jinja
fastapi_pluggable_auth/email/templates.py
fastapi_pluggable_auth/email/tokens.py
fastapi_pluggable_auth/models.py
fastapi_pluggable_auth/poetry.lock
fastapi_pluggable_auth/routes/__init__.py
fastapi_pluggable_auth/routes/account.py
fastapi_pluggable_auth/routes/core.py
fastapi_pluggable_auth/routes/email.py
fastapi_pluggable_auth/routes/password.py
fastapi_pluggable_auth/routes/twofa.py
fastapi_pluggable_auth/schemas.py
fastapi_pluggable_auth/security/__init__.py
fastapi_pluggable_auth/security/hashing.py
fastapi_pluggable_auth/security/jwt.py
fastapi_pluggable_auth/security/totp.py
fastapi_pluggable_auth/tests/conftest.py
fastapi_pluggable_auth/tests/test_account_management.py
fastapi_pluggable_auth/tests/test_auth_flow.py
fastapi_pluggable_auth/tests/test_email_verify.py
fastapi_pluggable_auth/tests/test_password_reset.py
fastapi_pluggable_auth/tests/test_refresh_rotation.py
fastapi_pluggable_auth/tests/test_sender.py
fastapi_pluggable_auth/tests/test_totp.py
fastapi_pluggable_auth-0.1.6.dist-info/METADATA
fastapi_pluggable_auth-0.1.6.dist-info/WHEEL
fastapi_pluggable_auth-0.1.6.dist-info/RECORD
