Metadata-Version: 2.3
Name: fastapi_pluggable_auth
Version: 0.1.6
Summary: Module for Auth
License: MIT
Author: Taylor Andrews
Requires-Python: >=3.13,<4.0
Classifier: License :: OSI Approved :: MIT License
Classifier: Programming Language :: Python :: 3
Classifier: Programming Language :: Python :: 3.13
Requires-Dist: aiosmtplib (>=4.0.1,<5.0.0)
Requires-Dist: email-validator (>=2.2.0,<3.0.0)
Requires-Dist: fastapi (>=0.115.12,<0.116.0)
Requires-Dist: jinja2 (>=3.1.6,<4.0.0)
Requires-Dist: limits[redis] (>=3.5,<4.0)
Requires-Dist: passlib[bcrypt] (>=1.7.4,<2.0.0)
Requires-Dist: pydantic-settings (>=2.9.1,<3.0.0)
Requires-Dist: pyotp (>=2.9.0,<3.0.0)
Requires-Dist: python-jose[cryptography] (>=3.4.0,<4.0.0)
Requires-Dist: qrcode[pil] (>=8.1,<9.0)
Requires-Dist: redis (>=5.0,<6.0)
Requires-Dist: tortoise-orm[asyncpg] (>=0.25.0,<0.26.0)
